pyroll/interface_friction.py
pyroll_interface_friction-3.0.0.post1.dist-info/METADATA
pyroll_interface_friction-3.0.0.post1.dist-info/WHEEL
pyroll_interface_friction-3.0.0.post1.dist-info/licenses/LICENSE
pyroll_interface_friction-3.0.0.post1.dist-info/RECORD
