Metadata-Version: 2.3
Name: pyroll-interface-friction
Version: 3.0.0.post1
Summary: Plugin for PyRoll providing hooks for interface friction.
Author-email: Christoph Renzing <christoph.renzing@imf.tu-freiberg.de>
License-Expression: BSD-3-Clause
License-File: LICENSE
Requires-Python: <4.0,>=3.9
Requires-Dist: pyroll-core~=3.0
